OdooFlow/__init__.py
OdooFlow/sales_order.py
tests/__init__.py
tests/test_sales_order.py
OdooFlow-0.1.0.dist-info/LICENSE
OdooFlow-0.1.0.dist-info/METADATA
OdooFlow-0.1.0.dist-info/WHEEL
OdooFlow-0.1.0.dist-info/top_level.txt
OdooFlow-0.1.0.dist-info/RECORD
