Metadata-Version: 2.1
Name: OdooFlow
Version: 0.1.0
Summary: A package to create record's in Odoo simply and cleanly
Home-page: https://github.com/tunahorse/OdooFlow
Author: Fabian Anguiano
Author-email: fabiananguiano@gmail.com
Classifier: Programming Language :: Python :: 3
Classifier: License :: OSI Approved :: MIT License
Classifier: Operating System :: OS Independent
Requires-Python: >=3.6
License-File: LICENSE
Requires-Dist: python-dotenv
